data_weaver/__init__.py
data_weaver/main.py
data_weaver/transforms.py
data_weaver/utils.py
DataWeaver-1.0.7.dist-info/LICENSE
DataWeaver-1.0.7.dist-info/METADATA
DataWeaver-1.0.7.dist-info/WHEEL
DataWeaver-1.0.7.dist-info/top_level.txt
DataWeaver-1.0.7.dist-info/RECORD
