Metadata-Version: 2.1
Name: DataWeaver
Version: 1.0.7
Summary: DataWeaver is a Python library for mapping data and transform object to an other. It offers flexible field mapping through a simple configuration object, enabling easy data integration and transformation for analysis and processing.
Author-email: RICHARD Quentin <richard.quentin88@gmail.com>
License: MIT License
Project-URL: homepage, https://github.com/RICHARD-Quentin/DataWeaver
Classifier: Programming Language :: Python :: 3
Classifier: License :: OSI Approved :: MIT License
Classifier: Operating System :: OS Independent
License-File: LICENSE
Requires-Dist: aiofiles >=0.7.0
Requires-Dist: PyYAML >=5.4
